aim_platform_sdk/__init__.py
aim_platform_sdk/api_client.py
aim_platform_sdk/api_response.py
aim_platform_sdk/configuration.py
aim_platform_sdk/exceptions.py
aim_platform_sdk/pydantic.py
aim_platform_sdk/rest.py
aim_platform_sdk/api/__init__.py
aim_platform_sdk/api/default_api.py
aim_platform_sdk/models/__init__.py
aim_platform_sdk/models/agent.py
aim_platform_sdk/models/agents_response.py
aim_platform_sdk/models/artifact.py
aim_platform_sdk/models/artifacts_response.py
aim_platform_sdk/models/benchmark.py
aim_platform_sdk/models/benchmark_ticket.py
aim_platform_sdk/models/benchmarks_response.py
aim_platform_sdk/models/bid.py
aim_platform_sdk/models/bids_response.py
aim_platform_sdk/models/code.py
aim_platform_sdk/models/create_agent_request.py
aim_platform_sdk/models/create_artifact_request.py
aim_platform_sdk/models/create_benchmark_request.py
aim_platform_sdk/models/create_benchmark_ticket_request.py
aim_platform_sdk/models/create_bid_request.py
aim_platform_sdk/models/create_repository_request.py
aim_platform_sdk/models/create_ticket_request.py
aim_platform_sdk/models/create_user_request.py
aim_platform_sdk/models/error.py
aim_platform_sdk/models/error_links.py
aim_platform_sdk/models/errors_response.py
aim_platform_sdk/models/manage_user_artifact_request.py
aim_platform_sdk/models/manage_user_bid_request.py
aim_platform_sdk/models/repositories_response.py
aim_platform_sdk/models/repository.py
aim_platform_sdk/models/ticket.py
aim_platform_sdk/models/tickets_response.py
aim_platform_sdk/models/update_agent_request.py
aim_platform_sdk/models/update_repository_request.py
aim_platform_sdk/models/update_user_request.py
aim_platform_sdk/models/user.py
aim_platform_sdk/models/user_response.py
aim_platform_sdk-0.1.2.dist-info/METADATA
aim_platform_sdk-0.1.2.dist-info/WHEEL
aim_platform_sdk-0.1.2.dist-info/top_level.txt
aim_platform_sdk-0.1.2.dist-info/RECORD
