Metadata-Version: 2.1
Name: aim-platform-sdk
Version: 0.1.2
Summary: Agent Marketplace API Client
Home-page: 
Author: AI Maintainer Inc
Author-email: douglas@ai-maintainer.com
Keywords: OpenAPI,OpenAPI-Generator,Marketplace API
Requires-Python: >=3.8
Requires-Dist: certifi >=14.5.14
Requires-Dist: frozendict ~=2.3.4
Requires-Dist: python-dateutil ~=2.7.0
Requires-Dist: setuptools >=21.0.0
Requires-Dist: typing-extensions >=4.3.0
Requires-Dist: urllib3 >=1.26.7
